<?xml version="1.0" encoding="utf-8" ?>
<dwsync>
<file name="category.tpl" server="www.frostandco.com.au" local="128792241292174262" remote="128792241000000000" />
<file name="product.tpl" server="www.frostandco.com.au" local="128789601703895410" remote="128789601600000000" />
<file name="cart.tpl" server="www.frostandco.com.au" local="128775811658418870" remote="128775811200000000" />
<file name="checkout.tpl" server="www.frostandco.com.au" local="128786952174893592" remote="128786952000000000" />
<file name="deposit_info.tpl" server="www.frostandco.com.au" local="128775906911009590" remote="128775906600000000" />
<file name="login.tpl" server="www.lashesonline.com.au" local="128866653278775063" remote="128871622200000000" />
<file name="category.tpl" server="www.lashesonline.com.au" local="128871000149992303" remote="128871621000000000" />
<file name="cart.tpl" server="www.lashesonline.com.au" local="128871695669342969" remote="128871695400000000" />
<file name="checkout.tpl" server="www.lashesonline.com.au" local="128869026883401334" remote="128871621000000000" />
<file name="product.tpl" server="www.lashesonline.com.au" local="128871000081240543" remote="128871622200000000" />
<file name="deposit_info.tpl" server="www.lashesonline.com.au" local="128866651242785443" remote="128871622200000000" />
<file name="card_payment.tpl" server="www.lashesonline.com.au" local="128866650879182385" remote="128871620400000000" />
<file name="payment_email.tpl" server="www.lashesonline.com.au" local="128843313237018125" remote="128871622200000000" />
<file name="pear_error_runmode.tpl" server="www.lashesonline.com.au" local="128868177246637682" remote="128871622200000000" />
<file name="registration.tpl" server="www.lashesonline.com.au" local="128866776535625000" remote="128871622200000000" />
<file name="sub-categories1.html" server="www.lashesonline.com.au" local="128843313236705615" remote="128871622200000000" />
<file name="registration_fields.tpl" server="www.lashesonline.com.au" local="128867225631060162" remote="128871622200000000" />
<file name="category.tpl" server="scottysmakeup.com.au" local="129342563251256811" remote="129342166800000000" />
<file name="categories.tpl" server="scottysmakeup.com.au" local="129342561456992129" remote="129342165000000000" />
<file name="product.tpl" server="scottysmakeup.com.au" local="129342567367344799" remote="129342171000000000" />
</dwsync>